{
   "library" : {
      "localId" : "0",
      "annotation" : [ {
         "translatorVersion" : "3.10.0",
         "translatorOptions" : "EnableAnnotations,EnableLocators,DisableListDemotion,DisableListPromotion",
         "signatureLevel" : "Overloads",
         "type" : "CqlToElmInfo"
      }, {
         "type" : "Annotation",
         "s" : {
            "r" : "324",
            "s" : [ {
               "value" : [ "","library PHQ9ScoreLogic version '0.1.0'" ]
            } ]
         }
      } ],
      "identifier" : {
         "id" : "PHQ9ScoreLogic",
         "system" : "http://mtnlotus.com/uv/pco",
         "version" : "0.1.0"
      },
      "schemaIdentifier" : {
         "id" : "urn:hl7-org:elm",
         "version" : "r1"
      },
      "usings" : {
         "def" : [ {
            "localId" : "1",
            "localIdentifier" : "System",
            "uri" : "urn:hl7-org:elm-types:r1"
         }, {
            "localId" : "206",
            "locator" : "3:1-3:26",
            "localIdentifier" : "FHIR",
            "uri" : "http://hl7.org/fhir",
            "version" : "4.0.1",
            "annotation" : [ {
               "type" : "Annotation",
               "s" : {
                  "r" : "206",
                  "s" : [ {
                     "value" : [ "","using " ]
                  }, {
                     "s" : [ {
                        "value" : [ "FHIR" ]
                     } ]
                  }, {
                     "value" : [ " version '4.0.1'" ]
                  } ]
               }
            } ]
         } ]
      },
      "includes" : {
         "def" : [ {
            "localId" : "207",
            "locator" : "5:1-5:35",
            "localIdentifier" : "FHIRHelpers",
            "path" : "http://mtnlotus.com/uv/pco/FHIRHelpers",
            "version" : "4.0.1",
            "annotation" : [ {
               "type" : "Annotation",
               "s" : {
                  "r" : "207",
                  "s" : [ {
                     "value" : [ "","include " ]
                  }, {
                     "s" : [ {
                        "value" : [ "FHIRHelpers" ]
                     } ]
                  }, {
                     "value" : [ " version ","'4.0.1'" ]
                  } ]
               }
            } ]
         } ]
      },
      "parameters" : {
         "def" : [ {
            "localId" : "217",
            "locator" : "14:1-14:40",
            "name" : "response",
            "accessLevel" : "Public",
            "annotation" : [ {
               "type" : "Annotation",
               "s" : {
                  "r" : "217",
                  "s" : [ {
                     "value" : [ "","parameter ","response"," " ]
                  }, {
                     "r" : "218",
                     "s" : [ {
                        "value" : [ "QuestionnaireResponse" ]
                     } ]
                  } ]
               }
            } ],
            "parameterTypeSpecifier" : {
               "localId" : "218",
               "locator" : "14:20-14:40",
               "name" : "{http://hl7.org/fhir}QuestionnaireResponse",
               "type" : "NamedTypeSpecifier"
            }
         } ]
      },
      "codeSystems" : {
         "def" : [ {
            "localId" : "208",
            "locator" : "7:1-7:38",
            "name" : "LOINC",
            "id" : "http://loinc.org",
            "accessLevel" : "Public",
            "annotation" : [ {
               "type" : "Annotation",
               "s" : {
                  "r" : "208",
                  "s" : [ {
                     "value" : [ "","codesystem ","\"LOINC\"",": ","'http://loinc.org'" ]
                  } ]
               }
            } ]
         } ]
      },
      "codes" : {
         "def" : [ {
            "localId" : "209",
            "locator" : "9:1-9:42",
            "name" : "Not at all",
            "id" : "LA6568-5",
            "accessLevel" : "Public",
            "annotation" : [ {
               "type" : "Annotation",
               "s" : {
                  "r" : "209",
                  "s" : [ {
                     "value" : [ "","code ","\"Not at all\"",": ","'LA6568-5'"," from " ]
                  }, {
                     "r" : "210",
                     "s" : [ {
                        "value" : [ "\"LOINC\"" ]
                     } ]
                  } ]
               }
            } ],
            "codeSystem" : {
               "localId" : "210",
               "locator" : "9:36-9:42",
               "name" : "LOINC"
            }
         }, {
            "localId" : "211",
            "locator" : "10:1-10:44",
            "name" : "Several days",
            "id" : "LA6569-3",
            "accessLevel" : "Public",
            "annotation" : [ {
               "type" : "Annotation",
               "s" : {
                  "r" : "211",
                  "s" : [ {
                     "value" : [ "","code ","\"Several days\"",": ","'LA6569-3'"," from " ]
                  }, {
                     "r" : "212",
                     "s" : [ {
                        "value" : [ "\"LOINC\"" ]
                     } ]
                  } ]
               }
            } ],
            "codeSystem" : {
               "localId" : "212",
               "locator" : "10:38-10:44",
               "name" : "LOINC"
            }
         }, {
            "localId" : "213",
            "locator" : "11:1-11:55",
            "name" : "More than half the days",
            "id" : "LA6570-1",
            "accessLevel" : "Public",
            "annotation" : [ {
               "type" : "Annotation",
               "s" : {
                  "r" : "213",
                  "s" : [ {
                     "value" : [ "","code ","\"More than half the days\"",": ","'LA6570-1'"," from " ]
                  }, {
                     "r" : "214",
                     "s" : [ {
                        "value" : [ "\"LOINC\"" ]
                     } ]
                  } ]
               }
            } ],
            "codeSystem" : {
               "localId" : "214",
               "locator" : "11:49-11:55",
               "name" : "LOINC"
            }
         }, {
            "localId" : "215",
            "locator" : "12:1-12:48",
            "name" : "Nearly every day",
            "id" : "LA6571-9",
            "accessLevel" : "Public",
            "annotation" : [ {
               "type" : "Annotation",
               "s" : {
                  "r" : "215",
                  "s" : [ {
                     "value" : [ "","code ","\"Nearly every day\"",": ","'LA6571-9'"," from " ]
                  }, {
                     "r" : "216",
                     "s" : [ {
                        "value" : [ "\"LOINC\"" ]
                     } ]
                  } ]
               }
            } ],
            "codeSystem" : {
               "localId" : "216",
               "locator" : "12:42-12:48",
               "name" : "LOINC"
            }
         } ]
      },
      "contexts" : {
         "def" : [ {
            "localId" : "222",
            "locator" : "16:1-16:15",
            "name" : "Patient"
         } ]
      },
      "statements" : {
         "def" : [ {
            "localId" : "220",
            "locator" : "16:1-16:15",
            "name" : "Patient",
            "context" : "Patient",
            "expression" : {
               "localId" : "221",
               "type" : "SingletonFrom",
               "signature" : [ ],
               "operand" : {
                  "localId" : "219",
                  "locator" : "16:1-16:15",
                  "dataType" : "{http://hl7.org/fhir}Patient",
                  "templateId" : "http://hl7.org/fhir/StructureDefinition/Patient",
                  "type" : "Retrieve",
                  "include" : [ ],
                  "codeFilter" : [ ],
                  "dateFilter" : [ ],
                  "otherFilter" : [ ]
               }
            }
         }, {
            "localId" : "224",
            "locator" : "18:1-18:54",
            "name" : "QuestionnaireResponses",
            "context" : "Patient",
            "accessLevel" : "Public",
            "annotation" : [ {
               "type" : "Annotation",
               "s" : {
                  "r" : "224",
                  "s" : [ {
                     "value" : [ "","define ","QuestionnaireResponses",": " ]
                  }, {
                     "r" : "225",
                     "s" : [ {
                        "value" : [ "[","QuestionnaireResponse","]" ]
                     } ]
                  } ]
               }
            } ],
            "expression" : {
               "localId" : "225",
               "locator" : "18:32-18:54",
               "dataType" : "{http://hl7.org/fhir}QuestionnaireResponse",
               "templateId" : "http://hl7.org/fhir/StructureDefinition/QuestionnaireResponse",
               "type" : "Retrieve",
               "include" : [ ],
               "codeFilter" : [ ],
               "dateFilter" : [ ],
               "otherFilter" : [ ]
            }
         }, {
            "localId" : "227",
            "locator" : "22:1-30:5",
            "name" : "QuestionnaireResponse",
            "context" : "Patient",
            "accessLevel" : "Public",
            "annotation" : [ {
               "type" : "Annotation",
               "s" : {
                  "r" : "227",
                  "s" : [ {
                     "value" : [ "// Use the QuestionnaireResponse provided as a parameter if available\n// Otherwise look it up from the record\n","define ","\"QuestionnaireResponse\"",":\n  " ]
                  }, {
                     "r" : "228",
                     "s" : [ {
                        "value" : [ "if " ]
                     }, {
                        "r" : "231",
                        "s" : [ {
                           "r" : "229",
                           "s" : [ {
                              "value" : [ "response" ]
                           } ]
                        }, {
                           "value" : [ " is not null" ]
                        } ]
                     }, {
                        "value" : [ " then\n    " ]
                     }, {
                        "r" : "232",
                        "s" : [ {
                           "value" : [ "response" ]
                        } ]
                     }, {
                        "value" : [ "\n  else\n    " ]
                     }, {
                        "r" : "260",
                        "s" : [ {
                           "value" : [ "Last","(\n      " ]
                        }, {
                           "r" : "257",
                           "s" : [ {
                              "s" : [ {
                                 "r" : "233",
                                 "s" : [ {
                                    "r" : "234",
                                    "s" : [ {
                                       "r" : "234",
                                       "s" : [ {
                                          "value" : [ "[","QuestionnaireResponse","]" ]
                                       } ]
                                    } ]
                                 }, {
                                    "value" : [ " ","QR" ]
                                 } ]
                              } ]
                           }, {
                              "value" : [ "\n        " ]
                           }, {
                              "r" : "235",
                              "s" : [ {
                                 "value" : [ "where " ]
                              }, {
                                 "r" : "235",
                                 "s" : [ {
                                    "r" : "237",
                                    "s" : [ {
                                       "r" : "236",
                                       "s" : [ {
                                          "value" : [ "QR" ]
                                       } ]
                                    }, {
                                       "value" : [ "." ]
                                    }, {
                                       "r" : "237",
                                       "s" : [ {
                                          "value" : [ "questionnaire" ]
                                       } ]
                                    } ]
                                 }, {
                                    "value" : [ " ","="," " ]
                                 }, {
                                    "r" : "238",
                                    "s" : [ {
                                       "value" : [ "'http://loinc.org/q/44249-1'" ]
                                    } ]
                                 } ]
                              } ]
                           }, {
                              "value" : [ "\n        " ]
                           }, {
                              "r" : "247",
                              "s" : [ {
                                 "value" : [ "sort by " ]
                              }, {
                                 "r" : "246",
                                 "s" : [ {
                                    "r" : "243",
                                    "s" : [ {
                                       "value" : [ "(" ]
                                    }, {
                                       "r" : "243",
                                       "s" : [ {
                                          "r" : "244",
                                          "s" : [ {
                                             "value" : [ "authored" ]
                                          } ]
                                       }, {
                                          "value" : [ " as " ]
                                       }, {
                                          "r" : "245",
                                          "s" : [ {
                                             "value" : [ "FHIR",".","dateTime" ]
                                          } ]
                                       } ]
                                    }, {
                                       "value" : [ ")" ]
                                    } ]
                                 }, {
                                    "value" : [ " desc" ]
                                 } ]
                              } ]
                           } ]
                        }, {
                           "value" : [ "\n    )" ]
                        } ]
                     } ]
                  } ]
               }
            } ],
            "expression" : {
               "localId" : "228",
               "locator" : "23:3-30:5",
               "type" : "If",
               "condition" : {
                  "localId" : "231",
                  "locator" : "23:6-23:25",
                  "type" : "Not",
                  "signature" : [ ],
                  "operand" : {
                     "localId" : "230",
                     "locator" : "23:6-23:25",
                     "type" : "IsNull",
                     "signature" : [ ],
                     "operand" : {
                        "localId" : "229",
                        "locator" : "23:6-23:13",
                        "name" : "response",
                        "type" : "ParameterRef"
                     }
                  }
               },
               "then" : {
                  "localId" : "232",
                  "locator" : "24:5-24:12",
                  "name" : "response",
                  "type" : "ParameterRef"
               },
               "else" : {
                  "localId" : "260",
                  "locator" : "26:5-30:5",
                  "type" : "Last",
                  "signature" : [ ],
                  "source" : {
                     "localId" : "257",
                     "locator" : "27:7-29:48",
                     "type" : "Query",
                     "source" : [ {
                        "localId" : "233",
                        "locator" : "27:7-27:32",
                        "alias" : "QR",
                        "expression" : {
                           "localId" : "234",
                           "locator" : "27:7-27:29",
                           "dataType" : "{http://hl7.org/fhir}QuestionnaireResponse",
                           "templateId" : "http://hl7.org/fhir/StructureDefinition/QuestionnaireResponse",
                           "type" : "Retrieve",
                           "include" : [ ],
                           "codeFilter" : [ ],
                           "dateFilter" : [ ],
                           "otherFilter" : [ ]
                        }
                     } ],
                     "let" : [ ],
                     "relationship" : [ ],
                     "where" : {
                        "localId" : "235",
                        "locator" : "28:9-28:61",
                        "type" : "Equal",
                        "signature" : [ {
                           "localId" : "241",
                           "name" : "{urn:hl7-org:elm-types:r1}String",
                           "type" : "NamedTypeSpecifier"
                        }, {
                           "localId" : "242",
                           "name" : "{urn:hl7-org:elm-types:r1}String",
                           "type" : "NamedTypeSpecifier"
                        } ],
                        "operand" : [ {
                           "localId" : "239",
                           "name" : "ToString",
                           "libraryName" : "FHIRHelpers",
                           "type" : "FunctionRef",
                           "signature" : [ {
                              "localId" : "240",
                              "name" : "{http://hl7.org/fhir}uri",
                              "type" : "NamedTypeSpecifier"
                           } ],
                           "operand" : [ {
                              "localId" : "237",
                              "locator" : "28:15-28:30",
                              "path" : "questionnaire",
                              "scope" : "QR",
                              "type" : "Property"
                           } ]
                        }, {
                           "localId" : "238",
                           "locator" : "28:34-28:61",
                           "valueType" : "{urn:hl7-org:elm-types:r1}String",
                           "value" : "http://loinc.org/q/44249-1",
                           "type" : "Literal"
                        } ]
                     },
                     "sort" : {
                        "localId" : "247",
                        "locator" : "29:9-29:48",
                        "by" : [ {
                           "localId" : "246",
                           "locator" : "29:17-29:48",
                           "direction" : "desc",
                           "type" : "ByExpression",
                           "expression" : {
                              "localId" : "243",
                              "locator" : "29:17-29:43",
                              "strict" : false,
                              "type" : "As",
                              "signature" : [ ],
                              "operand" : {
                                 "localId" : "244",
                                 "locator" : "29:18-29:25",
                                 "name" : "authored",
                                 "type" : "IdentifierRef"
                              },
                              "asTypeSpecifier" : {
                                 "localId" : "245",
                                 "locator" : "29:30-29:42",
                                 "name" : "{http://hl7.org/fhir}dateTime",
                                 "type" : "NamedTypeSpecifier"
                              }
                           }
                        } ]
                     }
                  }
               }
            }
         }, {
            "localId" : "262",
            "locator" : "36:1-48:5",
            "name" : "Responses",
            "context" : "Patient",
            "accessLevel" : "Public",
            "annotation" : [ {
               "type" : "Annotation",
               "s" : {
                  "r" : "262",
                  "s" : [ {
                     "value" : [ "// NOTE: This ties this logic directly to this particular rendering of the Questionnaire.\n// Ideally the items would be filtered based on Code of the Item, rather than the LinkId,\n// but that would require pulling in the Questionnaire because the QuestionnaireResponse\n// only has the LinkId.\n","define ","\"Responses\"",":\n  " ]
                  }, {
                     "r" : "284",
                     "s" : [ {
                        "s" : [ {
                           "r" : "263",
                           "s" : [ {
                              "r" : "264",
                              "s" : [ {
                                 "s" : [ {
                                    "value" : [ "\"QuestionnaireResponse\"" ]
                                 } ]
                              } ]
                           }, {
                              "value" : [ " ","QR" ]
                           } ]
                        } ]
                     }, {
                        "value" : [ "\n    " ]
                     }, {
                        "r" : "265",
                        "s" : [ {
                           "value" : [ "return " ]
                        }, {
                           "r" : "283",
                           "s" : [ {
                              "s" : [ {
                                 "r" : "266",
                                 "s" : [ {
                                    "r" : "268",
                                    "s" : [ {
                                       "s" : [ {
                                          "value" : [ "QR",".","item" ]
                                       } ]
                                    } ]
                                 }, {
                                    "value" : [ " ","I" ]
                                 } ]
                              } ]
                           }, {
                              "value" : [ " " ]
                           }, {
                              "r" : "280",
                              "s" : [ {
                                 "value" : [ "where " ]
                              }, {
                                 "r" : "280",
                                 "s" : [ {
                                    "r" : "270",
                                    "s" : [ {
                                       "r" : "269",
                                       "s" : [ {
                                          "value" : [ "I" ]
                                       } ]
                                    }, {
                                       "value" : [ "." ]
                                    }, {
                                       "r" : "270",
                                       "s" : [ {
                                          "value" : [ "linkId" ]
                                       } ]
                                    } ]
                                 }, {
                                    "value" : [ " in " ]
                                 }, {
                                    "r" : "271",
                                    "s" : [ {
                                       "value" : [ "{\n      " ]
                                    }, {
                                       "r" : "272",
                                       "s" : [ {
                                          "value" : [ "'14363'" ]
                                       } ]
                                    }, {
                                       "value" : [ ", //'LittleInterest'\n      " ]
                                    }, {
                                       "r" : "273",
                                       "s" : [ {
                                          "value" : [ "'14364'" ]
                                       } ]
                                    }, {
                                       "value" : [ ", //'FeelingDown'\n      " ]
                                    }, {
                                       "r" : "274",
                                       "s" : [ {
                                          "value" : [ "'14365'" ]
                                       } ]
                                    }, {
                                       "value" : [ ", //'TroubleSleeping'\n      " ]
                                    }, {
                                       "r" : "275",
                                       "s" : [ {
                                          "value" : [ "'14366'" ]
                                       } ]
                                    }, {
                                       "value" : [ ", //'FeelingTired'\n      " ]
                                    }, {
                                       "r" : "276",
                                       "s" : [ {
                                          "value" : [ "'14367'" ]
                                       } ]
                                    }, {
                                       "value" : [ ", //'BadApetite'\n      " ]
                                    }, {
                                       "r" : "277",
                                       "s" : [ {
                                          "value" : [ "'14368'" ]
                                       } ]
                                    }, {
                                       "value" : [ ", //'FeelingBadAboutSelf'\n      " ]
                                    }, {
                                       "r" : "278",
                                       "s" : [ {
                                          "value" : [ "'14369'" ]
                                       } ]
                                    }, {
                                       "value" : [ ", //'TroubleConcetrating'\n      " ]
                                    }, {
                                       "r" : "279",
                                       "s" : [ {
                                          "value" : [ "'14370'" ]
                                       } ]
                                    }, {
                                       "value" : [ " //'MovingSpeaking'\n      // '14371' // HurtingSelf\n    }" ]
                                    } ]
                                 } ]
                              } ]
                           } ]
                        } ]
                     } ]
                  } ]
               }
            } ],
            "expression" : {
               "localId" : "284",
               "locator" : "37:3-48:5",
               "type" : "Query",
               "source" : [ {
                  "localId" : "263",
                  "locator" : "37:3-37:28",
                  "alias" : "QR",
                  "expression" : {
                     "localId" : "264",
                     "locator" : "37:3-37:25",
                     "name" : "QuestionnaireResponse",
                     "type" : "ExpressionRef"
                  }
               } ],
               "let" : [ ],
               "relationship" : [ ],
               "return" : {
                  "localId" : "265",
                  "locator" : "38:5-48:5",
                  "expression" : {
                     "localId" : "283",
                     "locator" : "38:12-48:5",
                     "type" : "Query",
                     "source" : [ {
                        "localId" : "266",
                        "locator" : "38:12-38:20",
                        "alias" : "I",
                        "expression" : {
                           "localId" : "268",
                           "locator" : "38:12-38:18",
                           "path" : "item",
                           "scope" : "QR",
                           "type" : "Property"
                        }
                     } ],
                     "let" : [ ],
                     "relationship" : [ ],
                     "where" : {
                        "localId" : "280",
                        "locator" : "38:22-48:5",
                        "type" : "In",
                        "signature" : [ ],
                        "operand" : [ {
                           "localId" : "281",
                           "name" : "ToString",
                           "libraryName" : "FHIRHelpers",
                           "type" : "FunctionRef",
                           "signature" : [ {
                              "localId" : "282",
                              "name" : "{http://hl7.org/fhir}string",
                              "type" : "NamedTypeSpecifier"
                           } ],
                           "operand" : [ {
                              "localId" : "270",
                              "locator" : "38:28-38:35",
                              "path" : "linkId",
                              "scope" : "I",
                              "type" : "Property"
                           } ]
                        }, {
                           "localId" : "271",
                           "locator" : "38:40-48:5",
                           "type" : "List",
                           "element" : [ {
                              "localId" : "272",
                              "locator" : "39:7-39:13",
                              "valueType" : "{urn:hl7-org:elm-types:r1}String",
                              "value" : "14363",
                              "type" : "Literal"
                           }, {
                              "localId" : "273",
                              "locator" : "40:7-40:13",
                              "valueType" : "{urn:hl7-org:elm-types:r1}String",
                              "value" : "14364",
                              "type" : "Literal"
                           }, {
                              "localId" : "274",
                              "locator" : "41:7-41:13",
                              "valueType" : "{urn:hl7-org:elm-types:r1}String",
                              "value" : "14365",
                              "type" : "Literal"
                           }, {
                              "localId" : "275",
                              "locator" : "42:7-42:13",
                              "valueType" : "{urn:hl7-org:elm-types:r1}String",
                              "value" : "14366",
                              "type" : "Literal"
                           }, {
                              "localId" : "276",
                              "locator" : "43:7-43:13",
                              "valueType" : "{urn:hl7-org:elm-types:r1}String",
                              "value" : "14367",
                              "type" : "Literal"
                           }, {
                              "localId" : "277",
                              "locator" : "44:7-44:13",
                              "valueType" : "{urn:hl7-org:elm-types:r1}String",
                              "value" : "14368",
                              "type" : "Literal"
                           }, {
                              "localId" : "278",
                              "locator" : "45:7-45:13",
                              "valueType" : "{urn:hl7-org:elm-types:r1}String",
                              "value" : "14369",
                              "type" : "Literal"
                           }, {
                              "localId" : "279",
                              "locator" : "46:7-46:13",
                              "valueType" : "{urn:hl7-org:elm-types:r1}String",
                              "value" : "14370",
                              "type" : "Literal"
                           } ]
                        } ]
                     }
                  }
               }
            }
         }, {
            "localId" : "285",
            "locator" : "53:1-60:5",
            "name" : "AnswerCardinality",
            "context" : "Patient",
            "accessLevel" : "Public",
            "type" : "FunctionDef",
            "annotation" : [ {
               "type" : "Annotation",
               "t" : [ {
                  "name" : "source",
                  "value" : "https://www.med.umich.edu/1info/FHP/practiceguides/depress/score.pdf"
               } ],
               "s" : {
                  "r" : "285",
                  "s" : [ {
                     "value" : [ "/*\n@source: https://www.med.umich.edu/1info/FHP/practiceguides/depress/score.pdf\n*/\n","define function \"AnswerCardinality\"(answer Coding):\n  " ]
                  }, {
                     "r" : "288",
                     "s" : [ {
                        "r" : "288",
                        "s" : [ {
                           "value" : [ "case\n    " ]
                        }, {
                           "r" : "289",
                           "s" : [ {
                              "value" : [ "when " ]
                           }, {
                              "r" : "290",
                              "s" : [ {
                                 "r" : "291",
                                 "s" : [ {
                                    "value" : [ "answer" ]
                                 } ]
                              }, {
                                 "value" : [ " ","~"," " ]
                              }, {
                                 "r" : "292",
                                 "s" : [ {
                                    "value" : [ "\"Not at all\"" ]
                                 } ]
                              } ]
                           }, {
                              "r" : "296",
                              "value" : [ " then ","0" ]
                           } ]
                        }, {
                           "value" : [ "\n    " ]
                        }, {
                           "r" : "297",
                           "s" : [ {
                              "value" : [ "when " ]
                           }, {
                              "r" : "298",
                              "s" : [ {
                                 "r" : "299",
                                 "s" : [ {
                                    "value" : [ "answer" ]
                                 } ]
                              }, {
                                 "value" : [ " ","~"," " ]
                              }, {
                                 "r" : "300",
                                 "s" : [ {
                                    "value" : [ "\"Several days\"" ]
                                 } ]
                              } ]
                           }, {
                              "r" : "304",
                              "value" : [ " then ","1" ]
                           } ]
                        }, {
                           "value" : [ "\n    " ]
                        }, {
                           "r" : "305",
                           "s" : [ {
                              "value" : [ "when " ]
                           }, {
                              "r" : "306",
                              "s" : [ {
                                 "r" : "307",
                                 "s" : [ {
                                    "value" : [ "answer" ]
                                 } ]
                              }, {
                                 "value" : [ " ","~"," " ]
                              }, {
                                 "r" : "308",
                                 "s" : [ {
                                    "value" : [ "\"More than half the days\"" ]
                                 } ]
                              } ]
                           }, {
                              "r" : "312",
                              "value" : [ " then ","2" ]
                           } ]
                        }, {
                           "value" : [ "\n    " ]
                        }, {
                           "r" : "313",
                           "s" : [ {
                              "value" : [ "when " ]
                           }, {
                              "r" : "314",
                              "s" : [ {
                                 "r" : "315",
                                 "s" : [ {
                                    "value" : [ "answer" ]
                                 } ]
                              }, {
                                 "value" : [ " ","~"," " ]
                              }, {
                                 "r" : "316",
                                 "s" : [ {
                                    "value" : [ "\"Nearly every day\"" ]
                                 } ]
                              } ]
                           }, {
                              "r" : "320",
                              "value" : [ " then ","3" ]
                           } ]
                        }, {
                           "r" : "321",
                           "value" : [ "\n    else ","null","\n  end" ]
                        } ]
                     } ]
                  } ]
               }
            } ],
            "expression" : {
               "localId" : "288",
               "locator" : "54:3-60:5",
               "type" : "Case",
               "caseItem" : [ {
                  "localId" : "289",
                  "locator" : "55:5-55:37",
                  "when" : {
                     "localId" : "290",
                     "locator" : "55:10-55:30",
                     "type" : "Equivalent",
                     "signature" : [ {
                        "localId" : "294",
                        "name" : "{urn:hl7-org:elm-types:r1}Code",
                        "type" : "NamedTypeSpecifier"
                     }, {
                        "localId" : "295",
                        "name" : "{urn:hl7-org:elm-types:r1}Code",
                        "type" : "NamedTypeSpecifier"
                     } ],
                     "operand" : [ {
                        "localId" : "293",
                        "name" : "ToCode",
                        "libraryName" : "FHIRHelpers",
                        "type" : "FunctionRef",
                        "signature" : [ ],
                        "operand" : [ {
                           "localId" : "291",
                           "locator" : "55:10-55:15",
                           "name" : "answer",
                           "type" : "OperandRef"
                        } ]
                     }, {
                        "localId" : "292",
                        "locator" : "55:19-55:30",
                        "name" : "Not at all",
                        "type" : "CodeRef"
                     } ]
                  },
                  "then" : {
                     "localId" : "296",
                     "locator" : "55:37",
                     "valueType" : "{urn:hl7-org:elm-types:r1}Integer",
                     "value" : "0",
                     "type" : "Literal"
                  }
               }, {
                  "localId" : "297",
                  "locator" : "56:5-56:39",
                  "when" : {
                     "localId" : "298",
                     "locator" : "56:10-56:32",
                     "type" : "Equivalent",
                     "signature" : [ {
                        "localId" : "302",
                        "name" : "{urn:hl7-org:elm-types:r1}Code",
                        "type" : "NamedTypeSpecifier"
                     }, {
                        "localId" : "303",
                        "name" : "{urn:hl7-org:elm-types:r1}Code",
                        "type" : "NamedTypeSpecifier"
                     } ],
                     "operand" : [ {
                        "localId" : "301",
                        "name" : "ToCode",
                        "libraryName" : "FHIRHelpers",
                        "type" : "FunctionRef",
                        "signature" : [ ],
                        "operand" : [ {
                           "localId" : "299",
                           "locator" : "56:10-56:15",
                           "name" : "answer",
                           "type" : "OperandRef"
                        } ]
                     }, {
                        "localId" : "300",
                        "locator" : "56:19-56:32",
                        "name" : "Several days",
                        "type" : "CodeRef"
                     } ]
                  },
                  "then" : {
                     "localId" : "304",
                     "locator" : "56:39",
                     "valueType" : "{urn:hl7-org:elm-types:r1}Integer",
                     "value" : "1",
                     "type" : "Literal"
                  }
               }, {
                  "localId" : "305",
                  "locator" : "57:5-57:50",
                  "when" : {
                     "localId" : "306",
                     "locator" : "57:10-57:43",
                     "type" : "Equivalent",
                     "signature" : [ {
                        "localId" : "310",
                        "name" : "{urn:hl7-org:elm-types:r1}Code",
                        "type" : "NamedTypeSpecifier"
                     }, {
                        "localId" : "311",
                        "name" : "{urn:hl7-org:elm-types:r1}Code",
                        "type" : "NamedTypeSpecifier"
                     } ],
                     "operand" : [ {
                        "localId" : "309",
                        "name" : "ToCode",
                        "libraryName" : "FHIRHelpers",
                        "type" : "FunctionRef",
                        "signature" : [ ],
                        "operand" : [ {
                           "localId" : "307",
                           "locator" : "57:10-57:15",
                           "name" : "answer",
                           "type" : "OperandRef"
                        } ]
                     }, {
                        "localId" : "308",
                        "locator" : "57:19-57:43",
                        "name" : "More than half the days",
                        "type" : "CodeRef"
                     } ]
                  },
                  "then" : {
                     "localId" : "312",
                     "locator" : "57:50",
                     "valueType" : "{urn:hl7-org:elm-types:r1}Integer",
                     "value" : "2",
                     "type" : "Literal"
                  }
               }, {
                  "localId" : "313",
                  "locator" : "58:5-58:43",
                  "when" : {
                     "localId" : "314",
                     "locator" : "58:10-58:36",
                     "type" : "Equivalent",
                     "signature" : [ {
                        "localId" : "318",
                        "name" : "{urn:hl7-org:elm-types:r1}Code",
                        "type" : "NamedTypeSpecifier"
                     }, {
                        "localId" : "319",
                        "name" : "{urn:hl7-org:elm-types:r1}Code",
                        "type" : "NamedTypeSpecifier"
                     } ],
                     "operand" : [ {
                        "localId" : "317",
                        "name" : "ToCode",
                        "libraryName" : "FHIRHelpers",
                        "type" : "FunctionRef",
                        "signature" : [ ],
                        "operand" : [ {
                           "localId" : "315",
                           "locator" : "58:10-58:15",
                           "name" : "answer",
                           "type" : "OperandRef"
                        } ]
                     }, {
                        "localId" : "316",
                        "locator" : "58:19-58:36",
                        "name" : "Nearly every day",
                        "type" : "CodeRef"
                     } ]
                  },
                  "then" : {
                     "localId" : "320",
                     "locator" : "58:43",
                     "valueType" : "{urn:hl7-org:elm-types:r1}Integer",
                     "value" : "3",
                     "type" : "Literal"
                  }
               } ],
               "else" : {
                  "localId" : "322",
                  "asType" : "{urn:hl7-org:elm-types:r1}Integer",
                  "type" : "As",
                  "signature" : [ ],
                  "operand" : {
                     "localId" : "321",
                     "locator" : "59:10-59:13",
                     "type" : "Null"
                  }
               }
            },
            "operand" : [ {
               "localId" : "287",
               "name" : "answer",
               "operandTypeSpecifier" : {
                  "localId" : "286",
                  "locator" : "53:44-53:49",
                  "name" : "{http://hl7.org/fhir}Coding",
                  "type" : "NamedTypeSpecifier"
               }
            } ]
         }, {
            "localId" : "324",
            "locator" : "62:1-63:72",
            "name" : "CalculateTotalScore",
            "context" : "Patient",
            "accessLevel" : "Public",
            "annotation" : [ {
               "type" : "Annotation",
               "s" : {
                  "r" : "324",
                  "s" : [ {
                     "value" : [ "","define ","\"CalculateTotalScore\"",":\n  " ]
                  }, {
                     "r" : "349",
                     "s" : [ {
                        "value" : [ "Sum","(" ]
                     }, {
                        "r" : "344",
                        "s" : [ {
                           "s" : [ {
                              "r" : "325",
                              "s" : [ {
                                 "r" : "326",
                                 "s" : [ {
                                    "s" : [ {
                                       "value" : [ "\"Responses\"" ]
                                    } ]
                                 } ]
                              }, {
                                 "value" : [ " ","R" ]
                              } ]
                           } ]
                        }, {
                           "value" : [ " " ]
                        }, {
                           "r" : "327",
                           "s" : [ {
                              "value" : [ "return all " ]
                           }, {
                              "r" : "342",
                              "s" : [ {
                                 "value" : [ "AnswerCardinality","(" ]
                              }, {
                                 "r" : "341",
                                 "s" : [ {
                                    "value" : [ "First","(" ]
                                 }, {
                                    "r" : "337",
                                    "s" : [ {
                                       "r" : "329",
                                       "s" : [ {
                                          "r" : "328",
                                          "s" : [ {
                                             "value" : [ "R" ]
                                          } ]
                                       }, {
                                          "value" : [ "." ]
                                       }, {
                                          "r" : "329",
                                          "s" : [ {
                                             "value" : [ "answer" ]
                                          } ]
                                       } ]
                                    }, {
                                       "value" : [ "." ]
                                    }, {
                                       "r" : "337",
                                       "s" : [ {
                                          "value" : [ "value" ]
                                       } ]
                                    } ]
                                 }, {
                                    "value" : [ ")" ]
                                 } ]
                              }, {
                                 "value" : [ ")" ]
                              } ]
                           } ]
                        } ]
                     }, {
                        "value" : [ ")" ]
                     } ]
                  } ]
               }
            } ],
            "expression" : {
               "localId" : "349",
               "locator" : "63:3-63:72",
               "type" : "Sum",
               "signature" : [ {
                  "localId" : "350",
                  "type" : "ListTypeSpecifier",
                  "elementType" : {
                     "localId" : "351",
                     "name" : "{urn:hl7-org:elm-types:r1}Integer",
                     "type" : "NamedTypeSpecifier"
                  }
               } ],
               "source" : {
                  "localId" : "344",
                  "locator" : "63:7-63:71",
                  "type" : "Query",
                  "source" : [ {
                     "localId" : "325",
                     "locator" : "63:7-63:19",
                     "alias" : "R",
                     "expression" : {
                        "localId" : "326",
                        "locator" : "63:7-63:17",
                        "name" : "Responses",
                        "type" : "ExpressionRef"
                     }
                  } ],
                  "let" : [ ],
                  "relationship" : [ ],
                  "return" : {
                     "localId" : "327",
                     "locator" : "63:21-63:71",
                     "distinct" : false,
                     "expression" : {
                        "localId" : "342",
                        "locator" : "63:32-63:71",
                        "name" : "AnswerCardinality",
                        "type" : "FunctionRef",
                        "signature" : [ ],
                        "operand" : [ {
                           "localId" : "343",
                           "asType" : "{http://hl7.org/fhir}Coding",
                           "type" : "As",
                           "signature" : [ ],
                           "operand" : {
                              "localId" : "341",
                              "locator" : "63:50-63:70",
                              "type" : "First",
                              "signature" : [ ],
                              "source" : {
                                 "localId" : "337",
                                 "locator" : "63:56-63:69",
                                 "type" : "Query",
                                 "source" : [ {
                                    "localId" : "336",
                                    "alias" : "$this",
                                    "expression" : {
                                       "localId" : "329",
                                       "locator" : "63:56-63:63",
                                       "path" : "answer",
                                       "scope" : "R",
                                       "type" : "Property"
                                    }
                                 } ],
                                 "let" : [ ],
                                 "relationship" : [ ],
                                 "where" : {
                                    "localId" : "333",
                                    "type" : "Not",
                                    "signature" : [ ],
                                    "operand" : {
                                       "localId" : "332",
                                       "type" : "IsNull",
                                       "signature" : [ ],
                                       "operand" : {
                                          "localId" : "331",
                                          "path" : "value",
                                          "type" : "Property",
                                          "source" : {
                                             "localId" : "330",
                                             "name" : "$this",
                                             "type" : "AliasRef"
                                          }
                                       }
                                    }
                                 },
                                 "return" : {
                                    "localId" : "338",
                                    "distinct" : false,
                                    "expression" : {
                                       "localId" : "335",
                                       "path" : "value",
                                       "type" : "Property",
                                       "source" : {
                                          "localId" : "334",
                                          "name" : "$this",
                                          "type" : "AliasRef"
                                       }
                                    }
                                 }
                              }
                           }
                        } ]
                     }
                  }
               }
            }
         } ]
      }
   }
}